finnotech/__init__.py
finnotech/_version.py
finnotech/app_settings.py
finnotech/apps.py
finnotech/constants.py
finnotech/forms.py
finnotech/mixins.py
finnotech/models.py
finnotech/urls.py
finnotech/utils.py
finnotech/views.py
finnotech/migrations/0001_initial.py
finnotech/migrations/0002_alter_finnotechrefresh_token_and_more.py
finnotech/migrations/__init__.py
finnotech/pyfinnotech/__init__.py
finnotech/pyfinnotech/api.py
finnotech/pyfinnotech/const.py
finnotech/pyfinnotech/exceptions.py
finnotech/pyfinnotech/responses.py
finnotech/pyfinnotech/token.py
finnotech/pyfinnotech/tests/__init__.py
finnotech/pyfinnotech/tests/helper.py
finnotech/pyfinnotech/tests/mock_api_server.py
finnotech/pyfinnotech/tests/test_card_to_iban.py
finnotech/pyfinnotech/tests/test_card_validation.py
finnotech/pyfinnotech/tests/test_client_credential_token.py
finnotech/pyfinnotech/tests/test_iban_validation.py
finnotech/pyfinnotech/tests/test_national_id_verification.py
finnotech/templates/finnotech/base.html
finnotech/templates/finnotech/clientauth_form.html
finnotech/templates/finnotech/finnotech_form.html
django_finnotech-0.3.5.dist-info/LICENSE
django_finnotech-0.3.5.dist-info/METADATA
django_finnotech-0.3.5.dist-info/WHEEL
django_finnotech-0.3.5.dist-info/top_level.txt
django_finnotech-0.3.5.dist-info/RECORD
